odoo/addons/l10n_it_withholding_tax_reason/README.rst
odoo/addons/l10n_it_withholding_tax_reason/__init__.py
odoo/addons/l10n_it_withholding_tax_reason/__manifest__.py
odoo/addons/l10n_it_withholding_tax_reason/i18n/l10n_it_withholding_tax_reason.pot
odoo/addons/l10n_it_withholding_tax_reason/models/__init__.py
odoo/addons/l10n_it_withholding_tax_reason/models/withholding_tax.py
odoo/addons/l10n_it_withholding_tax_reason/readme/CONTRIBUTORS.rst
odoo/addons/l10n_it_withholding_tax_reason/readme/DESCRIPTION.rst
odoo/addons/l10n_it_withholding_tax_reason/readme/INSTALL.rst
odoo/addons/l10n_it_withholding_tax_reason/static/description/icon.png
odoo/addons/l10n_it_withholding_tax_reason/static/description/index.html
odoo/addons/l10n_it_withholding_tax_reason/views/withholding_tax.xml
odoo14_addon_l10n_it_withholding_tax_reason-14.0.1.0.2.dist-info/METADATA
odoo14_addon_l10n_it_withholding_tax_reason-14.0.1.0.2.dist-info/WHEEL
odoo14_addon_l10n_it_withholding_tax_reason-14.0.1.0.2.dist-info/top_level.txt
odoo14_addon_l10n_it_withholding_tax_reason-14.0.1.0.2.dist-info/RECORD
